./README.md
./pyproject.toml
./sts/__init__.py
./sts/realtime.py
./tests/test_openai_realtime.py
getstream_plugins_openai-0.1.1.dist-info/METADATA
getstream_plugins_openai-0.1.1.dist-info/WHEEL
getstream_plugins_openai-0.1.1.dist-info/RECORD
