Metadata-Version: 2.4
Name: getstream-plugins-openai
Version: 0.1.1
Summary: OpenAI plugin for GetStream
License-Expression: MIT
Requires-Python: >=3.10
Requires-Dist: getstream-plugins-common
Requires-Dist: getstream[webrtc]
Requires-Dist: openai[realtime]>=1.97.1
